a_pandas_ex_loc_no_exceptions/LICENSE
a_pandas_ex_loc_no_exceptions/README.MD
a_pandas_ex_loc_no_exceptions/__init__.py
a_pandas_ex_loc_no_exceptions/requirements.txt
a_pandas_ex_loc_no_exceptions/thirdparty.json
a_pandas_ex_loc_no_exceptions-0.10.dist-info/LICENSE.rst
a_pandas_ex_loc_no_exceptions-0.10.dist-info/METADATA
a_pandas_ex_loc_no_exceptions-0.10.dist-info/WHEEL
a_pandas_ex_loc_no_exceptions-0.10.dist-info/top_level.txt
a_pandas_ex_loc_no_exceptions-0.10.dist-info/RECORD
