Metadata-Version: 2.1
Name: a-pandas-ex-loc-no-exceptions
Version: 0.10
Summary: Search through all columns of a DataFrame without worrying about Exceptions
Home-page: https://github.com/hansalemaos/a_pandas_ex_loc_no_exceptions
Author: Johannes Fischer
Author-email: <aulasparticularesdealemaosp@gmail.com>
License: MIT
Keywords: loc,df.loc,Pandas,DataFrame,Exception
Classifier: Development Status :: 4 - Beta
Classifier: Programming Language :: Python :: 3 :: Only
Classifier: Programming Language :: Python :: 3.9
Classifier: Topic :: Scientific/Engineering :: Visualization
Classifier: Topic :: Software Development :: Libraries :: Python Modules
Classifier: Topic :: Text Editors :: Text Processing
Classifier: Topic :: Text Processing :: General
Classifier: Topic :: Text Processing :: Indexing
Classifier: Topic :: Text Processing :: Filters
Classifier: Topic :: Utilities
License-File: LICENSE.rst
Requires-Dist: pandas
